pyaci/__init__.py
pyaci/core.py
pyaci/errors.py
pyaci/filters.py
pyaci/options.py
pyaci/query.py
pyaci/templating.py
pyaci/utils.py
pyaci/static/style.css
pyaci/templates/audit-view.html
pyaci/templates/mo-view.html
pyaci/templates/query.html
cisco_pyaci-1.1.2.dist-info/METADATA
cisco_pyaci-1.1.2.dist-info/WHEEL
cisco_pyaci-1.1.2.dist-info/licenses/LICENSE
cisco_pyaci-1.1.2.dist-info/licenses/NOTICE
cisco_pyaci-1.1.2.dist-info/RECORD
